langchain_llm_api/__init__.py
langchain_llm_api/embeddings.py
langchain_llm_api/llm.py
langchain_llm_api-0.0.1.dist-info/LICENSE
langchain_llm_api-0.0.1.dist-info/METADATA
langchain_llm_api-0.0.1.dist-info/WHEEL
langchain_llm_api-0.0.1.dist-info/RECORD
