Metadata-Version: 2.1
Name: langchain-llm-api
Version: 0.0.1
Summary: Wrappers around LLM API models and embeddings clients.
Home-page: https://github.com/1b5d/langchain-llm-api
License: MIT
Author: 1b5d
Author-email: 8110504+1b5d@users.noreply.github.com
Requires-Python: >=3.8.1,<4.0.0
Classifier: License :: OSI Approved :: MIT License
Classifier: Programming Language :: Python :: 3
Classifier: Programming Language :: Python :: 3.9
Classifier: Programming Language :: Python :: 3.10
Classifier: Programming Language :: Python :: 3.11
Requires-Dist: langchain (>=0.0,<0.1)
Requires-Dist: pydantic (>=1.10,<2.0)
Requires-Dist: requests (>=2.28,<3.0)
Requires-Dist: sseclient-py (>=1.7,<2.0)
Project-URL: Repository, https://github.com/1b5d/langchain-llm-api
